CHANGES.md
CONTRIBUTORS.md
LICENSE.GPL
MANIFEST.in
README.md
pyproject.toml
setup.py
docs/conf.py
docs/index.rst
examples/export.cfg
examples/import.cfg
src/transmogrify/__init__.py
src/transmogrify.dexterity.egg-info/PKG-INFO
src/transmogrify.dexterity.egg-info/SOURCES.txt
src/transmogrify.dexterity.egg-info/dependency_links.txt
src/transmogrify.dexterity.egg-info/entry_points.txt
src/transmogrify.dexterity.egg-info/namespace_packages.txt
src/transmogrify.dexterity.egg-info/not-zip-safe
src/transmogrify.dexterity.egg-info/requires.txt
src/transmogrify.dexterity.egg-info/top_level.txt
src/transmogrify/dexterity/__init__.py
src/transmogrify/dexterity/configure.zcml
src/transmogrify/dexterity/converters.py
src/transmogrify/dexterity/converters.zcml
src/transmogrify/dexterity/interfaces.py
src/transmogrify/dexterity/schemareader.py
src/transmogrify/dexterity/schemaupdater.py
src/transmogrify/dexterity/serializer.py
src/transmogrify/dexterity/testing.py
src/transmogrify/dexterity/translation.py
src/transmogrify/dexterity/pipelines/__init__.py
src/transmogrify/dexterity/pipelines/configure.zcml
src/transmogrify/dexterity/pipelines/csvimport.cfg
src/transmogrify/dexterity/pipelines/export.cfg
src/transmogrify/dexterity/pipelines/import.cfg
src/transmogrify/dexterity/tests/__init__.py
src/transmogrify/dexterity/tests/pipelinescsvsource.txt
src/transmogrify/dexterity/tests/schemaupdater.txt
src/transmogrify/dexterity/tests/test_doctests.py
src/transmogrify/dexterity/tests/testconverters.py
src/transmogrify/dexterity/tests/testconverters_object.py
src/transmogrify/dexterity/tests/tests.cfg
src/transmogrify/dexterity/tests/tests.zcml