Metadata-Version: 2.1
Name: transmogrify.dexterity
Version: 3.0.0
Summary: A transmogrifier blueprint for updating dexterity objects
Home-page: https://github.com/collective/transmogrify.dexterity
Author: 4teamwork AG
Author-email: info@4teamwork.ch
License: GPL version 2
Project-URL: PyPI, https://pypi.python.org/pypi/transmogrify.dexterity
Project-URL: Source, https://github.com/collective/transmogrify.dexterity
Project-URL: Tracker, https://github.com/collective/transmogrify.dexterity/issues
Keywords: Python Plone CMS
Platform: UNKNOWN
Classifier: Development Status :: 6 - Mature
Classifier: Environment :: Web Environment
Classifier: Framework :: Plone :: 5.2
Classifier: Framework :: Plone :: 6.0
Classifier: Framework :: Plone :: Addon
Classifier: Framework :: Plone
Classifier: Framework :: Zope2
Classifier: Framework :: Zope3
Classifier: License :: OSI Approved :: GNU General Public License (GPL)
Classifier: License :: OSI Approved :: GNU General Public License v2 (GPLv2)
Classifier: Operating System :: OS Independent
Classifier: Programming Language :: Python :: 3.7
Classifier: Programming Language :: Python :: 3.8
Classifier: Programming Language :: Python :: 3.9
Classifier: Programming Language :: Python :: 3.10
Classifier: Programming Language :: Python :: 3.11
Classifier: Programming Language :: Python
Classifier: Topic :: Software Development :: Libraries :: Application Frameworks
Classifier: Topic :: Software Development :: Libraries :: Python Modules
Classifier: Topic :: Software Development :: Libraries :: Python Modules
Requires-Python: >=3.7
Provides-Extra: test
License-File: LICENSE.GPL
